cgcpp/__init__.py
cgcpp/__main__.py
cgcpp/build.py
cgcpp/lib_loader_python310.pyd
cgcpp/lib_loader_python311.pyd
cgcpp/lib_loader_python312.pyd
cgcpp/lib_loader_python39.pyd
cgcpp-1.8.2.dist-info/METADATA
cgcpp-1.8.2.dist-info/WHEEL
cgcpp-1.8.2.dist-info/top_level.txt
cgcpp-1.8.2.dist-info/RECORD
