Metadata-Version: 2.4
Name: cgcpp
Version: 1.8.2
Summary: CG C++ Support module
Author-email: Andriy Babak <ababak@gmail.com>
License-Expression: Apache-2.0
Project-URL: Homepage, https://github.com/ababak/cgcpp
Project-URL: Repository, https://github.com/ababak/cgcpp.git
